styled_logging/__init__.py
styled_logging/color.py
styled_logging/context.py
styled_logging/decorator.py
styled_logging/formatters.py
styled_logging/handlers.py
styled_logging/types.py
styled_logging-0.0.4.dist-info/LICENSE
styled_logging-0.0.4.dist-info/METADATA
styled_logging-0.0.4.dist-info/WHEEL
styled_logging-0.0.4.dist-info/top_level.txt
styled_logging-0.0.4.dist-info/RECORD
