Metadata-Version: 2.1
Name: styled-logging
Version: 0.0.4
Summary: Utilities for making log output look pretty
Home-page: https://github.com/eblocha/styled-logging
Author: Elliott Blocha
Author-email: eblocha@protonmail.me
Classifier: Programming Language :: Python :: 3
Classifier: License :: OSI Approved :: GNU General Public License v2 (GPLv2)
Classifier: Operating System :: OS Independent
License-File: LICENSE
Requires-Dist: pretty-traceback
